sundry/__init__.py
sundry/__version__.py
sundry/aws.py
sundry/dataclass_chain.py
sundry/date_time.py
sundry/dict_is_close.py
sundry/fb_locking.py
sundry/get_func_info.py
sundry/hash.py
sundry/is_main.py
sundry/robust_os.py
sundry/serializable.py
sundry/to_dynamodb.py
sundry/type_conversion.py
sundry/uidb32/__init__.py
sundry/uidb32/__main__.py
sundry/uidb32/uidb32.py
sundry-0.23.1.dist-info/LICENSE
sundry-0.23.1.dist-info/LICENSE.txt
sundry-0.23.1.dist-info/METADATA
sundry-0.23.1.dist-info/WHEEL
sundry-0.23.1.dist-info/top_level.txt
sundry-0.23.1.dist-info/RECORD
