Metadata-Version: 2.1
Name: sundry
Version: 0.23.1
Summary: miscellaneous code
Home-page: https://github.com/jamesabel/sundry
Author: James Abel
Author-email: j@abel.co
License: MIT License
Download-URL: https://github.com/jamesabel/sundry/archive/master.zip
Keywords: utility
Platform: UNKNOWN
Requires-Dist: python-dateutil
Requires-Dist: pillow
Requires-Dist: ismain
Requires-Dist: typeguard
Requires-Dist: boto3
